{
  "$schema": "https://wvw.dev/apps.schema.json",
  "store": {
    "name": "DodoApps",
    "developer": "DodoApps",
    "tagline": "Beautiful native macOS utilities",
    "url": "https://github.com/DodoApps",
    "github": "https://github.com/DodoApps"
  },
  "featured": [
    {
      "id": "dodoshot",
      "headline": "FEATURED",
      "title": "A beautiful screenshot tool for macOS",
      "subtitle": "Lightweight native macOS screenshot application with capture, annotation, and management capabilities. Inspired by CleanShot X, entirely free and open source."
    },
    {
      "id": "dodoclip",
      "headline": "FEATURED",
      "title": "A free clipboard manager for macOS",
      "subtitle": "A lightweight, native clipboard manager that automatically saves everything you copy and provides instant access to your clipboard history."
    },
    {
      "id": "dodopulse",
      "headline": "FEATURED",
      "title": "Real-time system monitoring in your menu bar",
      "subtitle": "A lightweight, native macOS menu bar app that displays real-time system metrics with beautiful mini graphs. Monitor CPU, memory, GPU, network, and more."
    },
    {
      "id": "dodopass",
      "headline": "FEATURED",
      "title": "Native macOS password manager",
      "subtitle": "A native macOS password manager built with SwiftUI, featuring local AES-256-GCM encryption with optional iCloud sync. Touch ID unlock, auto-lock, and smart clipboard."
    }
  ],
  "categories": [
    {
      "id": "macos",
      "name": "macOS Apps"
    },
    {
      "id": "productivity",
      "name": "Productivity"
    },
    {
      "id": "utilities",
      "name": "Utilities"
    },
    {
      "id": "business",
      "name": "Business"
    }
  ],
  "apps": [
    {
      "id": "dodoshot",
      "name": "DodoShot",
      "subtitle": "A beautiful screenshot tool for macOS",
      "description": "Lightweight native macOS screenshot application with capture, annotation, and management capabilities. Inspired by CleanShot X, entirely free and open source.",
      "longDescription": "Lightweight native macOS screenshot application with capture, annotation, and management capabilities. Inspired by CleanShot X, entirely free and open source.",
      "icon": "https://raw.githubusercontent.com/DodoApps/dodoshot/main/icon.png",
      "iconStyle": {
        "scale": 1.3,
        "objectFit": "cover",
        "borderRadius": "22%"
      },
      "category": [
        "macos",
        "productivity"
      ],
      "platform": "macOS",
      "price": "Free",
      "github": "https://github.com/DodoApps/dodoshot",
      "homepage": null,
      "language": "Swift",
      "stars": 13,
      "forks": 0,
      "downloadUrl": "https://github.com/DodoApps/dodoshot/releases/download/v1.2.9/DodoShot-1.2.9.dmg",
      "requirements": "macOS 14.0 or later",
      "features": [
        "Area, window, fullscreen capture",
        "Annotation tools with shapes and text",
        "OCR text extraction",
        "Floating screenshots"
      ],
      "screenshots": [
        "https://github.com/user-attachments/assets/a24b9914-0aab-4a03-993a-144069790290"
      ],
      "brew": "brew install --cask DodoApps/tap/dodoshot"
    },
    {
      "id": "dodoclip",
      "name": "DodoClip",
      "subtitle": "A free clipboard manager for macOS",
      "description": "A lightweight, native clipboard manager that automatically saves everything you copy and provides instant access to your clipboard history.",
      "longDescription": "A lightweight, native clipboard manager that automatically saves everything you copy and provides instant access to your clipboard history.",
      "icon": "https://raw.githubusercontent.com/DodoApps/dodoclip/main/icon.png",
      "iconStyle": {
        "scale": 1.3,
        "objectFit": "cover",
        "borderRadius": "22%"
      },
      "category": [
        "macos",
        "productivity"
      ],
      "platform": "macOS",
      "price": "Free",
      "github": "https://github.com/DodoApps/dodoclip",
      "homepage": null,
      "language": "Swift",
      "stars": 47,
      "forks": 0,
      "downloadUrl": "https://github.com/DodoApps/dodoclip/releases/download/v1.2.2/DodoClip-1.2.2.dmg",
      "requirements": "macOS 14.0 or later",
      "features": [
        "Clipboard history with search",
        "OCR for images",
        "Paste stack for sequential pasting",
        "Privacy controls"
      ],
      "screenshots": [
        "https://github.com/user-attachments/assets/f281b654-a0a2-4883-b09c-21aa2cd3efb4"
      ],
      "brew": "brew install --cask bluewave-labs/tap/dodoclip"
    },
    {
      "id": "dodopulse",
      "name": "DodoPulse",
      "subtitle": "Real-time system monitoring in your menu bar",
      "description": "A lightweight, native macOS menu bar app that displays real-time system metrics with beautiful mini graphs. Monitor CPU, memory, GPU, network, and more.",
      "longDescription": "A lightweight, native macOS menu bar app that displays real-time system metrics with beautiful mini graphs. Monitor CPU, memory, GPU, network, and more.",
      "icon": "https://raw.githubusercontent.com/DodoApps/dodopulse/525b81f/icon.png",
      "iconStyle": {
        "scale": 1.3,
        "objectFit": "cover",
        "borderRadius": "22%"
      },
      "category": [
        "macos",
        "utilities"
      ],
      "platform": "macOS",
      "price": "Free",
      "github": "https://github.com/DodoApps/dodopulse",
      "homepage": null,
      "language": "Swift",
      "stars": 101,
      "forks": 0,
      "downloadUrl": "https://github.com/DodoApps/dodopulse/releases/download/v1.1.0/DodoPulse-1.1.0.dmg",
      "requirements": "macOS 12.0 or later",
      "features": [
        "CPU, memory, GPU monitoring",
        "Network speed tracking",
        "Battery and fan status",
        "Beautiful mini graphs"
      ],
      "screenshots": [
        "https://github.com/user-attachments/assets/6868a0ac-1d01-45aa-84d7-8d21dc0daa6b"
      ],
      "brew": "brew install --cask dodoapps/tap/dodopulse"
    },
    {
      "id": "dodotidy",
      "name": "DodoTidy",
      "subtitle": "A native macOS system cleaner",
      "description": "A native macOS application for system monitoring, disk analysis, and cleanup. Remove caches, logs, and temporary files with multiple safety mechanisms.",
      "longDescription": "A native macOS application for system monitoring, disk analysis, and cleanup. Remove caches, logs, and temporary files with multiple safety mechanisms.",
      "icon": "https://raw.githubusercontent.com/DodoApps/dodotidy/main/dodotidy.png",
      "iconStyle": {
        "scale": 1.3,
        "objectFit": "cover",
        "borderRadius": "22%"
      },
      "category": [
        "macos",
        "utilities"
      ],
      "platform": "macOS",
      "price": "Free",
      "github": "https://github.com/DodoApps/dodotidy",
      "homepage": null,
      "language": "Swift",
      "stars": 71,
      "forks": 0,
      "downloadUrl": "https://github.com/DodoApps/dodotidy/releases/download/v1.0.5/DodoTidy-1.0.5.dmg",
      "requirements": "macOS 14.0 or later",
      "features": [
        "Cache and log cleanup",
        "Disk space visualization",
        "System optimization",
        "Safe trash-based deletion"
      ],
      "screenshots": [],
      "brew": "brew install --cask dodoapps/tap/dodotidy"
    },
    {
      "id": "dodocount",
      "name": "DodoCount",
      "subtitle": "Google Analytics in your menu bar",
      "description": "A beautiful macOS menubar app for Google Analytics 4 and Search Console. Quick access to visitor data and search metrics.",
      "longDescription": "A beautiful macOS menubar app for Google Analytics 4 and Search Console. Quick access to visitor data and search metrics.",
      "icon": "https://raw.githubusercontent.com/DodoApps/dodocount/main/dodocount.png",
      "iconStyle": {
        "scale": 1.3,
        "objectFit": "cover",
        "borderRadius": "22%"
      },
      "category": [
        "business",
        "macos"
      ],
      "platform": "macOS",
      "price": "Free",
      "github": "https://github.com/DodoApps/dodocount",
      "homepage": null,
      "language": "Swift",
      "stars": 0,
      "forks": 0,
      "downloadUrl": "https://github.com/DodoApps/dodocount/releases/download/v1.1.0/DodoCount-1.1.0.dmg",
      "requirements": "macOS 14.0 or later",
      "features": [
        "Real-time visitor tracking",
        "Search Console integration",
        "Today vs yesterday comparison",
        "Multiple property support"
      ],
      "screenshots": [],
      "brew": "brew install --cask DodoApps/tap/dodocount"
    },
    {
      "id": "dodonest",
      "name": "DodoNest",
      "subtitle": "Organize your menu bar items",
      "description": "A native macOS application for organizing and rearranging your menu bar items through drag-and-drop functionality and search.",
      "longDescription": "A native macOS application for organizing and rearranging your menu bar items through drag-and-drop functionality and search.",
      "icon": "https://raw.githubusercontent.com/DodoApps/dodonest/main/icon.png",
      "iconStyle": {
        "scale": 1.3,
        "objectFit": "cover",
        "borderRadius": "22%"
      },
      "category": [
        "macos",
        "utilities"
      ],
      "platform": "macOS",
      "price": "Free",
      "github": "https://github.com/DodoApps/dodonest",
      "homepage": null,
      "language": "Swift",
      "stars": 2,
      "forks": 0,
      "downloadUrl": "https://github.com/DodoApps/dodonest/releases/download/v1.1.0/DodoNest-1.1.0.dmg",
      "requirements": "macOS 14.0 or later",
      "features": [
        "Visual menu bar layout",
        "Drag-and-drop reordering",
        "Search functionality",
        "Real-time sync"
      ],
      "screenshots": [
        "https://raw.githubusercontent.com/DodoApps/dodonest/main/assets/screenshot.png"
      ],
      "brew": "brew install --cask dodoapps/tap/dodonest"
    },
    {
      "id": "dodopass",
      "name": "DodoPass",
      "subtitle": "Native macOS password manager",
      "description": "A native macOS password manager built with SwiftUI, featuring local AES-256-GCM encryption with optional iCloud sync. Touch ID unlock, auto-lock, and smart clipboard.",
      "longDescription": "A native macOS password manager built with SwiftUI, featuring local AES-256-GCM encryption with optional iCloud sync. Touch ID unlock, auto-lock, and smart clipboard.",
      "icon": "https://raw.githubusercontent.com/DodoApps/dodopass/main/icon.png",
      "iconStyle": {
        "scale": 1.3,
        "objectFit": "cover",
        "borderRadius": "22%"
      },
      "category": [
        "macos",
        "utilities"
      ],
      "platform": "macOS",
      "price": "Free",
      "github": "https://github.com/DodoApps/dodopass",
      "homepage": null,
      "language": "Swift",
      "stars": 0,
      "forks": 0,
      "downloadUrl": "https://github.com/DodoApps/dodopass/releases/download/v1.0.0/DodoPass-1.0.0.dmg",
      "requirements": "macOS 14.0 or later",
      "features": [
        "AES-256-GCM encryption",
        "Touch ID unlock",
        "Optional iCloud sync",
        "Auto-lock on inactivity"
      ],
      "screenshots": [],
      "brew": "brew install --cask dodoapps/tap/dodopass"
    }
  ]
}
